featureserver.cgi
featureserver.fcgi
featureserver_http_server.py
featureserver_install_config.py
setup.py
FeatureServer/Server.py
FeatureServer/__init__.py
FeatureServer.egg-info/PKG-INFO
FeatureServer.egg-info/SOURCES.txt
FeatureServer.egg-info/dependency_links.txt
FeatureServer.egg-info/not-zip-safe
FeatureServer.egg-info/top_level.txt
FeatureServer/DataSource/BerkeleyDB.py
FeatureServer/DataSource/DBM.py
FeatureServer/DataSource/Flickr.py
FeatureServer/DataSource/OGR.py
FeatureServer/DataSource/OSM.py
FeatureServer/DataSource/PostGIS.py
FeatureServer/DataSource/SQLite.py
FeatureServer/DataSource/Twitter.py
FeatureServer/DataSource/VersionedPostGIS.py
FeatureServer/DataSource/WFS.py
FeatureServer/DataSource/__init__.py
FeatureServer/Feature/Feature.py
FeatureServer/Feature/__init__.py
FeatureServer/Service/ArcGML.py
FeatureServer/Service/GeoJSON.py
FeatureServer/Service/GeoRSS.py
FeatureServer/Service/HTML.py
FeatureServer/Service/JSON.py
FeatureServer/Service/KML.py
FeatureServer/Service/OSM.py
FeatureServer/Service/WFS.py
FeatureServer/Service/__init__.py
