Metadata-Version: 1.0
Name: FeatureServer
Version: 1.12
Summary: A server for geographic features on the web.
Home-page: http://featureserver.org/
Author: MetaCarta Labs
Author-email: labs+featureserver@metacarta.com
License: Clear BSD
Platform: UNKNOWN
